disband/__init__.py
disband/client.py
disband/enums.py
disband/http.py
disband/relationship.py
disband/state.py
disband/user.py
disband.py-0.2.0.dist-info/DESCRIPTION.rst
disband.py-0.2.0.dist-info/METADATA
disband.py-0.2.0.dist-info/RECORD
disband.py-0.2.0.dist-info/WHEEL
disband.py-0.2.0.dist-info/metadata.json
disband.py-0.2.0.dist-info/top_level.txt
